{
  "must_subscribe_intro": "🔔 Извините, вы должны подписаться на следующие каналы:",
  "after_subscribe_press": "➡️ После подписки нажмите:",
  "i_subscribed_button": "✅ Я подписался, проверить сейчас",
  "server_not_found": "❌ Сервер не найден.",
  "bot_already_running": "⚠️ Бот уже запущен на этом сервере.",
  "searching_server": "⏳ Поиск информации о сервере...",
  "unsupported_protocol": "❌ Протокол Bedrock ({{protocol}}) не поддерживается.",
  "server_found_and_starting": "✅ Сервер найден (v{{version}}).\n⏳ Запуск бота...",
  "bot_disconnected": "Бот отключён от сервера",
  "check_plugin": "Пожалуйста, убедитесь, что ваш плагин включён ✅",
  "bot_now_active": "✅ Бот активен на сервере {{serverName}}",
  "failed_connect": "❌ Не удалось подключиться к серверу. Проверьте, что сервер онлайн и данные верны.",
  "send_ip_prompt": "Отправьте IP или домен сервера.\nПример: play.example.com",
  "cancel_button": "❌ Отмена и возврат",
  "operation_cancelled": "Операция отменена.",
  "send_port_prompt": "IP сохранён. Теперь отправьте номер порта (например: 19132):",
  "port_must_be_number": "❌ Порт должен быть числом. Пожалуйста, введите корректный порт.",
  "max_servers_reached": "❌ Вы не можете добавить более 3 серверов.",
  "back_to_main": "🔙 Назад в главное меню",
  "server_already_added": "⚠️ Вы уже добавили этот сервер.",
  "server_added_by_other": "⚠️ Этот сервер уже добавлен другим пользователем. Вы не можете добавить его.",
  "server_added_success": "✅ Сервер \"{{name}}\" успешно добавлен!",
  "error_adding_server": "❌ Ошибка при добавлении сервера. Пожалуйста, попробуйте снова.",
  "send_channel_with_at": "Отправьте имя канала с @ (пример: @Aternos_24)\nОтправьте /cancel для отмены.",
  "channel_format_invalid": "Неверный формат. Имя канала должно начинаться с @",
  "channel_added": "✅ Канал {{channel}} добавлен. Все пользователи будут повторно проверены.",
  "send_channel_to_delete": "Отправьте имя канала для удаления (с @)\nОтправьте /cancel для отмены.",
  "channel_removed": "✅ Канал {{channel}} удалён. Все пользователи будут повторно проверены.",
  "no_servers_registered": "В боте пока нет зарегистрированных серверов.",
  "all_servers_page": "🖥️ Показать все серверы (страница {{page}} из {{totalPages}})",
  "unknown": "Неизвестно",
  "server_owner": "Владелец сервера",
  "server_type": "Тип",
  "previous": "Назад",
  "next": "Далее",
  "back_button": "🔙 Назад",
  "send_broadcast_message": "Отправьте сообщение, которое хотите разослать всем.\nОтправьте /cancel для отмены.",
  "pin_enabled": "📌 Закрепление: Включено",
  "pin_disabled": "📌 Закрепление: Отключено",
  "broadcast_choose_settings": "Выберите настройки рассылки и нажмите Отправить:",
  "cancelled": "Отменено",
  "broadcast_cancelled": "Рассылка отменена.",
  "sending": "Отправка...",
  "broadcast_no_message": "❌ Нет сообщения для рассылки.",
  "broadcast_sending": "Рассылка отправляется...",
  "broadcast_done": "✅ Рассылка завершена.",
  "sent_to": "Отправлено",
  "failed": "Не удалось",
  "pin_results": "Результаты закрепления",
  "pinned": "Закреплено",
  "pin_failed": "Не удалось закрепить",
  "ban_user": "для бана пользователя",
  "unban_user": "для разбана пользователя",
  "info_user": "для просмотра информации",
  "send_user_id_for": "Отправьте ID пользователя",
  "cancel_hint": "Отправьте /cancel для отмены",
  "invalid_id": "Неверный ID.",
  "cannot_apply_to_main_dev": "Нельзя применить это действие к основному разработчику.",
  "user_not_found": "Пользователь не найден.",
  "user_banned": "✅ Пользователь {{username}} был забанен.",
  "user_unbanned": "✅ Пользователь {{username}} был разбанен.",
  "user_info_header": "👤 Информация о пользователе:",
  "user_id_label": "User ID",
  "username_label": "Username",
  "is_admin_label": "Admin",
  "is_banned_label": "Banned",
  "joined_label": "Joined",
  "servers_label": "Servers",
  "delete_all_servers": "🗑 Удалить все серверы",
  "add_as_admin": "добавить как админа",
  "remove_admin": "удалить из админов",
  "send_version_name": "Отправьте имя версии (напр.: 1.21.1).",
  "send_protocol_number": "Отправьте номер протокола.",
  "protocol_must_be_number": "Номер протокола должен быть числом.",
  "version_added": "✅ Версия успешно добавлена!",
  "protocol_exists": "❌ Ошибка: протокол уже существует.",
  "unexpected_error": "❌ Неожиданная ошибка.",
  "send_protocol_to_delete": "Отправьте номер протокола для удаления.\nОтправьте /cancel для отмены.",
  "protocol_deleted": "✅ Версия удалена.",
  "protocol_not_found": "❌ Версия с таким протоколом не найдена.",
  "how_to_use_text": "📚 Как добавить сервер:\n\n1. Нажмите ➕ Добавить сервер\n2. Отправьте IP сервера (например: play.example.com)\n3. Отправьте порт сервера (например: 19132)\n4. Убедитесь, что плагин включён на вашем сервере\n\nПримечания:\n- Сервер должен быть онлайн при добавлении\n- Макс. 3 сервера на пользователя\n\nДля поддержки присоединяйтесь: @Aternos_24",
  "bot_under_maintenance": "⚠️ Бот в настоящее время на техническом обслуживании.",
  "you_are_banned": "❌ Вы заблокированы и не можете использовать этого бота.",
  "message_expired": "This message has expired. Please try again from the main menu.",
  "checking": "Проверка...",
  "thanks_for_subscribing": "🎉 Спасибо за подписку! Теперь вы можете использовать бота. Нажмите /start.",
  "still_not_subscribed": "❌ Вы все еще не подписаны на все каналы.",
  "subscribe_first": "❌ Пожалуйста, подпишитесь сначала на требуемые каналы!",
  "welcome_message": "• Добро пожаловать в Player Bot 🔮\nЯ держу ваш сервер Minecraft онлайн 24/7 🛎\n\nВыберите из меню:",
  "my_servers": "🎮 Мои серверы",
  "add_server": "➕ Добавить сервер",
  "how_to_use_button": "❓ Как использовать",
  "admin_panel": "👑 Панель администратора",
  "max_servers_reached_alert": "❌ Вы не можете добавить более 3 серверов. Пожалуйста, удалите один прежде чем добавить новый.",
  "no_bedrock_servers": "У вас нет добавленных Bedrock серверов.",
  "add_server_now": "➕ Добавить сервер сейчас",
  "choose_server": "Выберите сервер для управления:",
  "refresh": "🔄 Обновить",
  "sending_start_command": "Отправка команды запуска...",
  "fetching_info": "Получение информации...",
  "cannot_reach_server": "❌ Невозможно связаться с сервером сейчас.",
  "confirm_delete_server": "Вы уверены, что хотите удалить этот сервер?",
  "yes_delete": "Да, удалить",
  "no_cancel": "Нет, отменить",
  "deleting": "Удаление...",
  "server_deleted": "✅ Сервер удалён.",
  "bot_not_active": "❌ Бот в данный момент не активен.",
  "uptime_text": "⏱ Время работы бота:\n\n{{hours}} часов {{minutes}} минут {{seconds}} секунд",
  "not_admin": "❌ Вы не администратор.",
  "admin_panel_welcome": "👑 Добро пожаловать в панель управления разработчика.",
  "stats": "📊 Статистика",
  "broadcast_all": "📣 Трансляция всем",
  "manage_users": "👤 Управление пользователями",
  "view_all_servers": "🖥️ Просмотр всех серверов",
  "manage_versions": "⚙️ Управление версиями",
  "manage_admins": "🔑 Управление администраторами",
  "system_status": "🖥️ Статус системы",
  "bot_settings": "🔧 Настройки бота",
  "manage_required_channels": "📢 Управление обязательными каналами",
  "current_channels": "Текущие каналы:",
  "no_required_channels": "Нет обязательных каналов в настоящее время.",
  "add_channel": "➕ Добавить канал",
  "remove_channel": "➖ Удалить канал",
  "stats_text": "📊 Статистика бота:\n\nПользователей: {{totalUsers}}\nАдминов: {{adminUsers}}\nЗаблокировано: {{bannedUsers}}\nСерверов: {{totalServers}}\nАктивных ботов: {{activeBots}}",
  "system_status_text": "🖥️ Статус системы:\n\nCPU: {{cpu}} %\nRAM: {{used}} MB / {{total}} MB\nRAM бота: {{botRam}} MB\nВремя работы: {{uptimeMinutes}} минут",
  "error_fetching_status": "❌ Ошибка при получении статуса системы.",
  "user_no_servers": "❌ Этот пользователь не имеет серверов.",
  "all_servers_deleted": "✅ Все серверы удалены.",
  "error_deleting_servers": "⚠️ Ошибка при удалении серверов.",
  "manage_users_title": "👤 Управление пользователями",
  "ban": "🚫 Заблокировать",
  "unban": "✅ Разблокировать",
  "view_info": "ℹ️ Просмотр информации",
  "current_admins": "👑 Текущие админы:",
  "no_admins": "Пока нет админов.",
  "main_dev": "Главный разработчик",
  "admin_label": "Admin",
  "and_more": "и ещё {{n}}",
  "total_admins": "Всего админов: {{n}}",
  "add_admin": "➕ Добавить админа",
  "remove_admin": "➖ Убрать админа",
  "manage_versions_title": "⚙️ Управление версиями Minecraft.",
  "list_all": "📋 Показать все",
  "add_version": "➕ Добавить",
  "delete_version": "➖ Удалить",
  "fetching_list": "Получение списка...",
  "bedrock_label": "Bedrock",
  "fetching": "Получение...",
  "bot_settings_title": "🔧 Общие настройки бота",
  "bot_status": "Статус бота",
  "on": "Включен",
  "off": "Выключен",
  "bot_status_changed": "Статус бота изменён на: {{status}}",
  "language_prompt": "Выберите язык / اختر لغتك:",
  "language": "🌐 Язык",
  "language_changed": "✅ Язык изменён на {{lang}}",
  "language_prompt_short": "Выберите язык:",
  "send_version_name": "Отправьте название версии:",
  "send_protocol_number": "Отправьте номер протокола:"
}